tfmodelserver/__init__.py
tfmodelserver/model.py
tfmodelserver/resolver.py
tfmodelserver/server.py
tfmodelserver/timer.py
tfmodelserver/utils.py
tfmodelserver-1.0.7.dist-info/METADATA
tfmodelserver-1.0.7.dist-info/WHEEL
tfmodelserver-1.0.7.dist-info/top_level.txt
tfmodelserver-1.0.7.dist-info/RECORD
