Metadata-Version: 2.1
Name: tfmodelserver
Version: 1.0.7
Summary: Libraries for easy bootstrapping TensorFlow server
Home-page: https://github.com/shygiants/tfmodelserver
Author: Sanghoon Yoon
Author-email: shygiants@gmail.com
License: UNKNOWN
Keywords: tensorflow,libraries
Platform: UNKNOWN
Classifier: Programming Language :: Python :: 3
Classifier: Programming Language :: Python :: 3.2
Classifier: Programming Language :: Python :: 3.3
Classifier: Programming Language :: Python :: 3.4
Classifier: Programming Language :: Python :: 3.5
Classifier: Programming Language :: Python :: 3.6
Classifier: Programming Language :: Python :: 3.7
Classifier: Programming Language :: Python :: 2.7
Requires-Python: >=2.7
Requires-Dist: Flask
Requires-Dist: flask-cors
Requires-Dist: numpy
Requires-Dist: requests
Requires-Dist: pytz
Requires-Dist: absl-py
Requires-Dist: Pillow
Provides-Extra: dev
Requires-Dist: tensorflow (==1.11.0) ; extra == 'dev'
